tkitAutoTokenizerPosition/AutoPos.py
tkitAutoTokenizerPosition/AutoTokenizerPosition.py
tkitAutoTokenizerPosition/__init__.py
tkitAutoTokenizerPosition/bio.py
tkitAutoTokenizerPosition/span.py
tkitAutoTokenizerPosition-0.0.0.616376824.dist-info/LICENSE
tkitAutoTokenizerPosition-0.0.0.616376824.dist-info/METADATA
tkitAutoTokenizerPosition-0.0.0.616376824.dist-info/WHEEL
tkitAutoTokenizerPosition-0.0.0.616376824.dist-info/top_level.txt
tkitAutoTokenizerPosition-0.0.0.616376824.dist-info/RECORD
