Metadata-Version: 2.1
Name: tkitAutoTokenizerPosition
Version: 0.0.0.616376824
Summary: Terry toolkit tkitAutoTokenizerPosition,
Home-page: https://docs.terrychan.org/tkit-AutoTokenizerPosition/index.html
Author: Terry Chan
Author-email: napoler2008@gmail.com
License: UNKNOWN
Platform: UNKNOWN
Requires-Dist: tqdm (==4.62.2)
Requires-Dist: numpy (==1.21.2)
Requires-Dist: regex (==2021.10.8)
Requires-Dist: pkuseg (>=0.0.25)
